ostree_push-1.2.0.data/scripts/ostree-receive-shell
otpush/__init__.py
otpush/push.py
otpush/receive.py
otpush/receive_legacy.py
ostree_push-1.2.0.dist-info/COPYING
ostree_push-1.2.0.dist-info/METADATA
ostree_push-1.2.0.dist-info/WHEEL
ostree_push-1.2.0.dist-info/entry_points.txt
ostree_push-1.2.0.dist-info/top_level.txt
ostree_push-1.2.0.dist-info/RECORD
