Metadata-Version: 2.1
Name: ostree-push
Version: 1.2.0
Summary: Push and receive OSTree commits
Home-page: https://github.com/dbnicholson/ostree-push
Author: Dan Nicholson
Author-email: dbn@endlessos.org
Classifier: Programming Language :: Python :: 3
Classifier: Programming Language :: Python :: 3.7
Classifier: Programming Language :: Python :: 3.8
Classifier: Programming Language :: Python :: 3.9
Classifier: Development Status :: 5 - Production/Stable
Classifier: License :: OSI Approved :: GNU General Public License v2 or later (GPLv2+)
Classifier: Operating System :: POSIX
Classifier: Topic :: Software Development :: Build Tools
Classifier: Topic :: System :: Archiving :: Mirroring
Classifier: Topic :: System :: Archiving :: Packaging
Classifier: Topic :: System :: Software Distribution
Requires-Python: >=3.7
License-File: COPYING
Requires-Dist: PyGObject
Requires-Dist: PyYAML
